{
  "feature_request": "Create a calculator for basic calculations",
  "run_dir": "output/calculator/20260715-130803",
  "status": "us-003-developer-iteration-2",
  "current_story_id": "us-003",
  "developer_iteration": 2,
  "last_feedback": "Fresh repair attempt. Use only this feedback plus the handoff context; do not rely on prior tool history.\nTests failed:\n# Test Report\n\nStatus: failed\nCommand: `python3 -m pytest /tests -q --junitxml=/tests/test-results.xml`\nExit code: 1\nCounts: 5 tests, 1 failures, 0 errors, 0 skipped\n\n## Pytest Output\n\n```text\n....F                                                                               [100%]\n======================================== FAILURES =========================================\n_________________________ test_clear_button_visible_and_behavior __________________________\n\n    def test_clear_button_visible_and_behavior():\n        \"\"\"\n        Covers criteria:\n          1. A 'Clear' or 'Reset' button is visible on the interface.\n          2. Clicking the button empties all input fields.\n          3. The result display area is cleared after clicking the button.\n          4. The calculator returns to its initial ready state without requiring a page refresh.\n        \"\"\"\n        # Criterion 1: Clear button visible on interface (HTTP smoke check)\n        with urllib.request.urlopen(f\"{BASE_URL}/\") as resp:\n            html = resp.read().decode(\"utf-8\")\n    \n        assert \"Clear\" in html, \"Clear button not found on the page.\"\n        assert 'id=\"clearBtn\"' in html, \"Clear button missing expected id='clearBtn'.\"\n    \n        # Criteria 2, 3, 4: Verify source-level behavior by reading source file directly.\n        src_path = \"/project/src/app.py\"\n>       with open(src_path) as f:\n             ^^^^^^^^^^^^^^\nE       FileNotFoundError: [Errno 2] No such file or directory: '/project/src/app.py'\n\ntest_us-003.py:25: FileNotFoundError\n================================= short test summary info =================================\nFAILED test_us-003.py::test_clear_button_visible_and_behavior - FileNotFoundError: [Errn...\n1 failed, 4 passed in 0.07s\n```\n\n\nFailing test file test_us-003.py (read-only, owned by the tester \u2014 fix the app so these tests pass, never touch /tests):\n\"\"\"Tests for US-003: Clear Inputs and Results.\"\"\"\nimport urllib.request\nimport os\n\nBASE_URL = os.environ.get(\"APP_URL\", \"http://localhost:57951\")\n\n\ndef test_clear_button_visible_and_behavior():\n    \"\"\"\n    Covers criteria:\n      1. A 'Clear' or 'Reset' button is visible on the interface.\n      2. Clicking the button empties all input fields.\n      3. The result display area is cleared after clicking the button.\n      4. The calculator returns to its initial ready state without requiring a page refresh.\n    \"\"\"\n    # Criterion 1: Clear button visible on interface (HTTP smoke check)\n    with urllib.request.urlopen(f\"{BASE_URL}/\") as resp:\n        html = resp.read().decode(\"utf-8\")\n\n    assert \"Clear\" in html, \"Clear button not found on the page.\"\n    assert 'id=\"clearBtn\"' in html, \"Clear button missing expected id='clearBtn'.\"\n\n    # Criteria 2, 3, 4: Verify source-level behavior by reading source file directly.\n    src_path = \"/project/src/app.py\"\n    with open(src_path) as f:\n        src = f.read()\n\n    # Criterion 2: Clicking empties all input fields\n    assert \"document.getElementById('num1').value = ''\" in src, \\\n        \"Clear handler does not empty num1.\"\n    assert \"document.getElementById('num2').value = ''\" in src, \\\n        \"Clear handler does not empty num2.\"\n\n    # Criterion 3: Result display area is cleared\n    assert \".result\" in src and \".remove()\" in src, \\\n        \"Clear handler does not remove result display.\"\n\n    # Criterion 4: Button type=\"button\" means no form submission / page refresh\n    assert 'type=\"button\"' in html and 'id=\"clearBtn\"' in html, \\\n        \"Clear button is not type='button'; may cause unwanted page refresh.\"\n"
}