{
  "feature_request": "I want to manage my todos",
  "run_dir": "output/todo-app/20260715-144706",
  "status": "us-001-developer-iteration-2",
  "current_story_id": "us-001",
  "developer_iteration": 2,
  "last_feedback": "Fresh repair attempt. Use only this feedback plus the handoff context; do not rely on prior tool history.\nServer/smoke check failed: Process status: CRASHED\n--- bg.log ---\n\n\nServer log (most recent):\n----------------------------------------\nException occurred during processing of request from ('127.0.0.1', 46816)\nTraceback (most recent call last):\n  File \"/opt/conda/lib/python3.11/socketserver.py\", line 691, in process_request_thread\n    self.finish_request(request, client_address)\n  File \"/opt/conda/lib/python3.11/socketserver.py\", line 361, in finish_request\n    self.RequestHandlerClass(request, client_address, self)\n  File \"/opt/conda/lib/python3.11/socketserver.py\", line 755, in __init__\n    self.handle()\n  File \"/opt/conda/lib/python3.11/http/server.py\", line 436, in handle\n    self.handle_one_request()\n  File \"/opt/conda/lib/python3.11/http/server.py\", line 424, in handle_one_request\n    method()\n  File \"/home/jovyan/ss26-kip/output/todo-app/20260715-144706/src/app.py\", line 84, in do_GET\n    html = render_page(snapshot)\n           ^^^^^^^^^^^^^^^^^^^^^\n  File \"/home/jovyan/ss26-kip/output/todo-app/20260715-144706/src/app.py\", line 32, in render_page\n    return '''<!DOCTYPE html>\n           ^^^^^^^^^^^^^^^^^^\nValueError: unsupported format character ';' (0x3b) at index 490\n----------------------------------------"
}